bd_metric/__init__.py
bd_metric/bjontegaard_metric.py
bd_metric-0.9.0.dist-info/LICENSE
bd_metric-0.9.0.dist-info/METADATA
bd_metric-0.9.0.dist-info/WHEEL
bd_metric-0.9.0.dist-info/top_level.txt
bd_metric-0.9.0.dist-info/RECORD
