Metadata-Version: 2.1
Name: bd-metric
Version: 0.9.0
Summary: Bjontegaard metric calculation
Home-page: https://github.com/shengbinmeng/Bjontegaard_metric
Author: Shengbin Meng
Author-email: shengbinmeng@gmail.com
License: UNKNOWN
Platform: UNKNOWN
Classifier: Programming Language :: Python
Classifier: Programming Language :: Python :: 2
Classifier: Programming Language :: Python :: 3
Classifier: License :: OSI Approved :: MIT License
Classifier: Operating System :: OS Independent
Requires-Dist: numpy
Requires-Dist: scipy
